jo/__init__.py
jo-0.0.7.dist-info/licenses/LICENSE
jo-0.0.7.dist-info/METADATA
jo-0.0.7.dist-info/WHEEL
jo-0.0.7.dist-info/top_level.txt
jo-0.0.7.dist-info/RECORD
