Metadata-Version: 2.4
Name: jo
Version: 0.0.7
Summary: Automatically making flask webservices from python objects
Home-page: https://github.com/t-c-w/jo
Author: Thor Whalen
License: apache-2.0
Platform: any
License-File: LICENSE
Dynamic: license-file
